setup.py
django_datadog.egg-info/PKG-INFO
django_datadog.egg-info/SOURCES.txt
django_datadog.egg-info/dependency_links.txt
django_datadog.egg-info/top_level.txt
djdatadog/__init__.py
djdatadog/helpers.py
djdatadog/middleware/__init__.py
djdatadog/middleware/request_handler.py