Metadata-Version: 1.0
Name: django-datadog
Version: 1.0
Summary: simple Django middleware for submitting timings and exceptions to Datadog.
Home-page: UNKNOWN
Author: Chris Heisel
Author-email: cheisel@kabbage.com
License: BSD
Platform: UNKNOWN
